CustomersMailCloud/Client.py
CustomersMailCloud/__init__.py
CustomersMailCloud-1.1.dist-info/LICENSE
CustomersMailCloud-1.1.dist-info/METADATA
CustomersMailCloud-1.1.dist-info/WHEEL
CustomersMailCloud-1.1.dist-info/top_level.txt
CustomersMailCloud-1.1.dist-info/RECORD
