Metadata-Version: 2.1
Name: CustomersMailCloud
Version: 1.1
Summary: Python library for Customers Mail Cloud
Home-page: UNKNOWN
Author: Atsushi
Author-email: atsushi@moongift.jp
License: UNKNOWN
Platform: UNKNOWN
Classifier: Programming Language :: Python :: 3.7
Classifier: License :: OSI Approved :: MIT License
Classifier: Operating System :: OS Independent
